numba_inspector/__init__.py
numba_inspector/frontend/__init__.py
numba_inspector/frontend/annotate.py
numba_inspector/ipython_magic.py
numba_inspector-0.0.5.dist-info/METADATA
numba_inspector-0.0.5.dist-info/WHEEL
numba_inspector-0.0.5.dist-info/RECORD
