Metadata-Version: 2.1
Name: numba-inspector
Version: 0.0.5
Summary: Visualize and Debug Numba compiled code in Jupyter
Author: Matthew Murray
Author-email: matthewmurray711@gmail.com
Requires-Python: >=3.10,<4.0
Classifier: Programming Language :: Python :: 3
Classifier: Programming Language :: Python :: 3.10
Classifier: Programming Language :: Python :: 3.11
Requires-Dist: notebook (>=6.5.4,<7.0.0)
Requires-Dist: numba (>=0.57.1,<0.58.0)
